Metadata-Version: 2.1
Name: stepanalyzer
Version: 0.3.1
Summary: Step Response analyzer
Home-page: https://github.com/AstroSayan/StepAnalyzer
Author: Sayan Das
Author-email: astrosayan8@gmail.com
License: MIT
Download-URL: https://github.com/AstroSayan/StepAnalyzer/archive/refs/tags/v0.3.1.tar.gz
Platform: UNKNOWN
Classifier: Programming Language :: Python :: 3
Classifier: License :: OSI Approved :: MIT License
Classifier: Operating System :: OS Independent
Requires-Python: >=3.6
